doct.py
doct-1.1.0.dist-info/LICENSE
doct-1.1.0.dist-info/METADATA
doct-1.1.0.dist-info/WHEEL
doct-1.1.0.dist-info/top_level.txt
doct-1.1.0.dist-info/RECORD
